<?xml version="1.0" encoding="UTF-8"?>
<databaseChangeLog
    xmlns="http://www.liquibase.org/xml/ns/dbchangelog"
    xmlns:xsi="http://www.w3.org/2001/XMLSchema-instance"
    xsi:schemaLocation="http://www.liquibase.org/xml/ns/dbchangelog
        https://www.liquibase.org/xml/ns/dbchangelog/dbchangelog-latest.xsd">

    <changeSet id="create-player-accounts-table" author="slobodan">
        <createTable tableName="player_accounts">
            <column name="id" type="uuid">
                <constraints primaryKey="true" nullable="false"/>
            </column>
            <column name="email" type="varchar(100)">
                <constraints nullable="false" unique="true"/>
            </column>
            <column name="password" type="varchar(255)">
                <constraints nullable="false"/>
            </column>
            <column name="first_name" type="varchar(50)"/>
            <column name="last_name" type="varchar(50)"/>
            <column name="birth_date" type="date">
                <constraints nullable="false"/>
            </column>
            <column name="timezone" type="varchar(50)"/>
            <column name="is_verified" type="boolean" defaultValueBoolean="false"/>
            <column name="is_banned" type="boolean" defaultValueBoolean="false"/>
            <column name="last_login_at" type="timestamp"/>
            <column name="created_at" type="timestamp" defaultValueDate="current_timestamp"/>
            <column name="updated_at" type="timestamp"/>
            <column name="version" type="integer"/>
        </createTable>
    </changeSet>

</databaseChangeLog>
